{
  "id": "emottr",
  "subreddit": "bulimia",
  "author": "deadcomefebruary",
  "created_utc": 1578649834.0,
  "title": "I haven't purged in 4 days!!",
  "selftext": "I'm drinking again, crying, and can't remember trig functions, but I've held down broccoli, a quarter piece of raspberry fritter, half a piece of egg patty, and salad with dressing!!",
  "url": "https://www.reddit.com/r/bulimia/comments/emottr/i_havent_purged_in_4_days/",
  "score": 83,
  "num_comments": 8,
  "comments": [
    {
      "id": "fdq5mw2",
      "author": "millennialpink_03",
      "body": "You should feel very proud of yourself! Now rejoice that your body is slowly learning to digest food again, that the bloated cheeks are slowly deflating, and your teeth are getting to do what they do!",
      "created_utc": 1578655921.0,
      "score": 8,
      "context": []
    },
    {
      "id": "fdqk2xj",
      "author": "None",
      "body": "\u2764\ufe0f\u2764\ufe0f\u2764\ufe0f Hope you continue. Very proud of you!!",
      "created_utc": 1578668581.0,
      "score": 2,
      "context": []
    },
    {
      "id": "fdqx2z3",
      "author": "SteelSabre1",
      "body": "Hell yeah brother",
      "created_utc": 1578676063.0,
      "score": 2,
      "context": []
    },
    {
      "id": "fduozpt",
      "author": "skinny_bitch_88",
      "body": "You are doing great!",
      "created_utc": 1578736557.0,
      "score": 2,
      "context": []
    },
    {
      "id": "fdzgr0l",
      "author": "lolwhymeh08",
      "body": "I'm so proud of you! Youre doing great! Great job!!",
      "created_utc": 1578790050.0,
      "score": 2,
      "context": []
    },
    {
      "id": "ffa2p8m",
      "author": "Joe_MOTS",
      "body": "That\u2019s awesome!  Every day is a victory :)",
      "created_utc": 1579726688.0,
      "score": 1,
      "context": []
    },
    {
      "id": "fdrx8gy",
      "author": "deadcomefebruary",
      "body": "Thank you tons!! 5 days now!!",
      "created_utc": 1578691103.0,
      "score": 2,
      "context": [
        {
          "id": "fdq5mw2",
          "author": "millennialpink_03",
          "body": "You should feel very proud of yourself! Now rejoice that your body is slowly learning to digest food again, that the bloated cheeks are slowly deflating, and your teeth are getting to do what they do!",
          "created_utc": 1578655921.0
        }
      ]
    },
    {
      "id": "fdrx9rm",
      "author": "deadcomefebruary",
      "body": "Thank you!!",
      "created_utc": 1578691122.0,
      "score": 1,
      "context": [
        {
          "id": "fdqk2xj",
          "author": "None",
          "body": "\u2764\ufe0f\u2764\ufe0f\u2764\ufe0f Hope you continue. Very proud of you!!",
          "created_utc": 1578668581.0
        }
      ]
    }
  ]
}