{
  "id": "jumj0f",
  "subreddit": "bulimia",
  "author": "wolfinthedaylight",
  "created_utc": 1605449898.0,
  "title": "Yesterday I hit my 3 month mark! Sent it to my best friend, but forgot to post on here.",
  "selftext": "",
  "url": "https://i.redd.it/y43sdvlaxez51.jpg",
  "score": 113,
  "num_comments": 10,
  "comments": [
    {
      "id": "gcegru1",
      "author": "Trick-Pin1883",
      "body": "What app is this ? :)) I\u2019d like to use also :)",
      "created_utc": 1605457880.0,
      "score": 12,
      "context": []
    },
    {
      "id": "gcekf8d",
      "author": "gaudinockerl",
      "body": "I am so proud of you!",
      "created_utc": 1605459919.0,
      "score": 7,
      "context": []
    },
    {
      "id": "gcejvg3",
      "author": "_bizong",
      "body": "Amazing!!",
      "created_utc": 1605459615.0,
      "score": 7,
      "context": []
    },
    {
      "id": "gcezvke",
      "author": "ducklover83",
      "body": "Wow dude!! That\u2019s amazing! Keep it up and be kind to yourself, you got this :)",
      "created_utc": 1605468102.0,
      "score": 4,
      "context": []
    },
    {
      "id": "gcfiu3s",
      "author": "haleighhuman",
      "body": "That\u2019s awesome!!!! Great , amazing , phenomenal job !!! \u2764\ufe0f",
      "created_utc": 1605477724.0,
      "score": 4,
      "context": []
    },
    {
      "id": "gcfk13d",
      "author": "bluebiz2",
      "body": "Wonderful job! You\u2019re  beautiful and you are so so strong. Don\u2019t ever forget how strong you are! You can do anything if you push yourself.",
      "created_utc": 1605478343.0,
      "score": 3,
      "context": []
    },
    {
      "id": "gcg8hh7",
      "author": "Music4lif",
      "body": "Why\u2019d you mark this small success, this is a fucking accomplishment",
      "created_utc": 1605491043.0,
      "score": 2,
      "context": []
    },
    {
      "id": "gcgy75q",
      "author": "trulycrazy",
      "body": "CONGRATULATIONS this is amazing!!! We\u2019re all proud of you xx",
      "created_utc": 1605506416.0,
      "score": 2,
      "context": []
    },
    {
      "id": "gcem70o",
      "author": "wolfinthedaylight",
      "body": "It\u2019s called \u201cI Am Sober\u201d \ud83d\ude42",
      "created_utc": 1605460904.0,
      "score": 15,
      "context": [
        {
          "id": "gcegru1",
          "author": "Trick-Pin1883",
          "body": "What app is this ? :)) I\u2019d like to use also :)",
          "created_utc": 1605457880.0
        }
      ]
    },
    {
      "id": "geh3hoc",
      "author": "Trick-Pin1883",
      "body": "Thankyou !!\ud83e\udd7a\ud83d\udc96",
      "created_utc": 1606991578.0,
      "score": 1,
      "context": [
        {
          "id": "gcegru1",
          "author": "Trick-Pin1883",
          "body": "What app is this ? :)) I\u2019d like to use also :)",
          "created_utc": 1605457880.0
        },
        {
          "id": "gcem70o",
          "author": "wolfinthedaylight",
          "body": "It\u2019s called \u201cI Am Sober\u201d \ud83d\ude42",
          "created_utc": 1605460904.0
        }
      ]
    }
  ]
}