{
  "id": "mjoxct",
  "subreddit": "bulimia",
  "author": "acoh97",
  "created_utc": 1617510188.0,
  "title": "I can't wait until someone invents a time machine so that I can go back and yank my fingers out of my mouth the first time I decided to ruin my life.",
  "selftext": "Let me know if you have any leads. Not asking for a friend, because I don't have one. :) :) :)",
  "url": "https://www.reddit.com/r/bulimia/comments/mjoxct/i_cant_wait_until_someone_invents_a_time_machine/",
  "score": 176,
  "num_comments": 17,
  "comments": [
    {
      "id": "gtbwzkz",
      "author": "luca-nicoletti",
      "body": "You don't know how much I feel the same. Damn that time I thought: \"Why don't you just puke everything up? It's better that way\"",
      "created_utc": 1617526377.0,
      "score": 20,
      "context": []
    },
    {
      "id": "gtbzp60",
      "author": "lacroixlite",
      "body": "I hate that I got back into it. That i got back into it so *easily*.\n\nIf it's any consultation, we were all probably feeling pretty low and desperate when we started, because why else do it? We weren't trying to hurt ourselves. We were trying to cope.",
      "created_utc": 1617529203.0,
      "score": 17,
      "context": []
    },
    {
      "id": "gtc404r",
      "author": "hellohello_0606",
      "body": "I remember it was someone who helped me when I got too drunk  and then went from there...",
      "created_utc": 1617533519.0,
      "score": 5,
      "context": []
    },
    {
      "id": "gtcvp0p",
      "author": "Technical-Click-4302",
      "body": "Yeah when I can\u2019t puke I just sit on the bathroom floor crying usually I can\u2019t even cry, then I cut my self not with any blood just enough so it will leave a mark for some days",
      "created_utc": 1617551849.0,
      "score": 7,
      "context": []
    },
    {
      "id": "gtblpt5",
      "author": "mtdunca",
      "body": "According to Endgame, that's not how time travel works unfortunately.",
      "created_utc": 1617515489.0,
      "score": 9,
      "context": []
    },
    {
      "id": "gtd3c6w",
      "author": "its_tanya",
      "body": "I couldn\u2019t agree more. The struggle is so real and just gets worse as you get older. I don\u2019t even binge anymore, some days I just purge everything I eat",
      "created_utc": 1617555747.0,
      "score": 3,
      "context": []
    },
    {
      "id": "gtd9g62",
      "author": "None",
      "body": "this .",
      "created_utc": 1617558851.0,
      "score": 3,
      "context": []
    },
    {
      "id": "gtdkmom",
      "author": "None",
      "body": "So fucking relatable, it's a hell on earth",
      "created_utc": 1617564655.0,
      "score": 3,
      "context": []
    },
    {
      "id": "gtfvpb5",
      "author": "just3bored",
      "body": "Thank you so much for this, I think you just saved my life\n\n\nTw: might be kinda triggering \n\nAfter restricting for a while, last night I binged. I felt SO SO terrible. And for the first time, I seriously considered purging. I tried to think about reasons not to, but I couldn\u2019t find any. So I went to this subreddit, just trying to stop myself from making such a big mistake and I\u2019m so thankful I found this. I read it, breathed, And realized \u201cwtf am I doing\u201d. So I took some sleeping pills and forced myself to sleep.\n\nI\u2019m writing this in the next morning, with more mental clarity. And I just want to say thank you so much",
      "created_utc": 1617620262.0,
      "score": 3,
      "context": []
    },
    {
      "id": "gtcdhfe",
      "author": "m1dh3th3r0",
      "body": "I wish I could do the same for my partner \ud83d\ude14",
      "created_utc": 1617541350.0,
      "score": 2,
      "context": []
    },
    {
      "id": "gtcp47u",
      "author": "jekyllcorvus",
      "body": "I first learned about bulimia in high school when we were showed some hbo special starring Clarista Flockhart about being a teen hiding her ED.\n\nI decided to go home and try it. I knew right then and there that there was no coming back. It\u2019s been close to twenty years later and I wish I could tell that young kid to stop and lose weight the right way. But here we are.",
      "created_utc": 1617548401.0,
      "score": 2,
      "context": []
    },
    {
      "id": "gtdpy87",
      "author": "shlanmeister",
      "body": "I think about this all the fucking time",
      "created_utc": 1617567430.0,
      "score": 2,
      "context": []
    },
    {
      "id": "gtf5xqv",
      "author": "ZowiHowms",
      "body": "Yes! For the longest time I thought I was the only one who made the conscious decision to do this to themselves. I thought it would be easy.. I just need to do this lose the weight and then stop and be happy again. Oh how I was wrong. You should go back and encourage myself to do things the healthy way instead of trying to take it easy way out. This \"easy weight loss\" is the hardest thing in the world.",
      "created_utc": 1617597121.0,
      "score": 1,
      "context": []
    },
    {
      "id": "gtdrurx",
      "author": "mamomoop",
      "body": "Ah the good ol tactical chunder \ud83d\ude43",
      "created_utc": 1617568422.0,
      "score": 1,
      "context": [
        {
          "id": "gtc404r",
          "author": "hellohello_0606",
          "body": "I remember it was someone who helped me when I got too drunk  and then went from there...",
          "created_utc": 1617533519.0
        }
      ]
    },
    {
      "id": "gtg87kh",
      "author": "acoh97",
      "body": "I\u2019m sooo happy you decided against it\u2764\ufe0f \nI just gotta have my \u201cwtf am I doing\u201d moments *prior* to self sabotage lol. But for real, thank you for sharing and keep going, you got this \ud83d\udcaa",
      "created_utc": 1617628607.0,
      "score": 2,
      "context": [
        {
          "id": "gtfvpb5",
          "author": "just3bored",
          "body": "Thank you so much for this, I think you just saved my life\n\n\nTw: might be kinda triggering \n\nAfter restricting for a while, last night I binged. I felt SO SO terrible. And for the first time, I seriously considered purging. I tried to think about reasons not to, but I couldn\u2019t find any. So I went to this subreddit, just trying to stop myself from making such a big mistake and I\u2019m so thankful I found this. I read it, breathed, And realized \u201cwtf am I doing\u201d. So I took some sleeping pills and forced myself to sleep.\n\nI\u2019m writing this in the next morning, with more mental clarity. And I just want to say thank you so much",
          "created_utc": 1617620262.0
        }
      ]
    },
    {
      "id": "gtg8q3d",
      "author": "just3bored",
      "body": "Lmaoo, sending you tons of strength!!",
      "created_utc": 1617628890.0,
      "score": 1,
      "context": [
        {
          "id": "gtfvpb5",
          "author": "just3bored",
          "body": "Thank you so much for this, I think you just saved my life\n\n\nTw: might be kinda triggering \n\nAfter restricting for a while, last night I binged. I felt SO SO terrible. And for the first time, I seriously considered purging. I tried to think about reasons not to, but I couldn\u2019t find any. So I went to this subreddit, just trying to stop myself from making such a big mistake and I\u2019m so thankful I found this. I read it, breathed, And realized \u201cwtf am I doing\u201d. So I took some sleeping pills and forced myself to sleep.\n\nI\u2019m writing this in the next morning, with more mental clarity. And I just want to say thank you so much",
          "created_utc": 1617620262.0
        },
        {
          "id": "gtg87kh",
          "author": "acoh97",
          "body": "I\u2019m sooo happy you decided against it\u2764\ufe0f \nI just gotta have my \u201cwtf am I doing\u201d moments *prior* to self sabotage lol. But for real, thank you for sharing and keep going, you got this \ud83d\udcaa",
          "created_utc": 1617628607.0
        }
      ]
    }
  ]
}