{
  "id": "v3dlh3",
  "subreddit": "fuckeatingdisorders",
  "author": "Alternative_Lie_8826",
  "created_utc": 1654189473.0,
  "title": "My mom told me she gained 15 pounds",
  "selftext": "And I didn\u2019t even notice it. She looks the same. Not that noticeable weight gain is even a bad thing, but the weight gain you\u2019re seeing on the scale probably doesn\u2019t compare to what\u2019s actually visible.\n\nAnd before you come after my mom for talking about numbers, she was telling me that in the context of \u201cguess what? It doesn\u2019t matter and I love myself just as much.\u201d",
  "url": "https://www.reddit.com/r/fuckeatingdisorders/comments/v3dlh3/my_mom_told_me_she_gained_15_pounds/",
  "score": 123,
  "num_comments": 9,
  "comments": [
    {
      "id": "iaxzvgc",
      "author": "dollszn",
      "body": "definitely needed to hear this, like i know logically 10 lbs isn\u2019t noticeable at all my brain is just stupid",
      "created_utc": 1654195805.0,
      "score": 48,
      "context": []
    },
    {
      "id": "iayhm4g",
      "author": "myceliumfriend",
      "body": "I neeeeeded this. Thank you. She sounds wonderful!",
      "created_utc": 1654203532.0,
      "score": 20,
      "context": []
    },
    {
      "id": "iaxygj7",
      "author": "mandanic",
      "body": "This is SO true! Important reminder.",
      "created_utc": 1654195210.0,
      "score": 11,
      "context": []
    },
    {
      "id": "iaxmhto",
      "author": "Elle241",
      "body": "Thanks for this reminder!",
      "created_utc": 1654190176.0,
      "score": 15,
      "context": []
    },
    {
      "id": "iaxw9og",
      "author": "keepmyheadabovewater",
      "body": "This is so true! We are our own worst critics, other people don\u2019t necessarily notice weight fluctuations.",
      "created_utc": 1654194273.0,
      "score": 6,
      "context": []
    },
    {
      "id": "iaz2365",
      "author": "lamna_ditropis",
      "body": "Thank you \u2661",
      "created_utc": 1654212903.0,
      "score": 3,
      "context": []
    },
    {
      "id": "iaza3s5",
      "author": "BedroomImpossible124",
      "body": "Thank you!!! I needed this so much today.",
      "created_utc": 1654216853.0,
      "score": 2,
      "context": []
    },
    {
      "id": "iayjqsg",
      "author": "Alternative_Lie_8826",
      "body": "She\u2019s awesome",
      "created_utc": 1654204494.0,
      "score": 15,
      "context": [
        {
          "id": "iayhm4g",
          "author": "myceliumfriend",
          "body": "I neeeeeded this. Thank you. She sounds wonderful!",
          "created_utc": 1654203532.0
        }
      ]
    }
  ]
}