{
  "id": "ybneyc",
  "subreddit": "fuckeatingdisorders",
  "author": "throwra738483",
  "created_utc": 1666545663.0,
  "title": "just ate McDonald\u2019s",
  "selftext": "and I FUCKING DID IT!!!! I ATE MCDONALDS!!! A WHOLE ASS MEAL!!! I didn\u2019t even want to purge it afterwards and I have ZERO guilt. im stunned rn. no desire to binge like I was so so terrified of before. I\u2019m so proud yall. y\u2019all it really is so worth it \u2764\ufe0f",
  "url": "https://www.reddit.com/r/fuckeatingdisorders/comments/ybneyc/just_ate_mcdonalds/",
  "score": 85,
  "num_comments": 7,
  "comments": [
    {
      "id": "ithifh8",
      "author": "None",
      "body": "Well done! I don't know you, but I wanted you to know that I am proud of you! \u2764",
      "created_utc": 1666548872.0,
      "score": 7,
      "context": []
    },
    {
      "id": "ithzotd",
      "author": "the_acid_lava_lamp",
      "body": "so proud of you!! honestly mcdonald\u2019s actually slaps, EDs are such liars lol",
      "created_utc": 1666555336.0,
      "score": 5,
      "context": []
    },
    {
      "id": "itil655",
      "author": "fmdkdnxksk",
      "body": "PROUD!!!",
      "created_utc": 1666563634.0,
      "score": 2,
      "context": []
    },
    {
      "id": "itilv6h",
      "author": "YoullNeverWalkAl0ne",
      "body": "I love Maccies!",
      "created_utc": 1666563928.0,
      "score": 2,
      "context": []
    },
    {
      "id": "itiwvej",
      "author": "marsmakesart",
      "body": "hell yeah!!!",
      "created_utc": 1666568720.0,
      "score": 1,
      "context": []
    },
    {
      "id": "itkaxh0",
      "author": "chazzz33",
      "body": "So proud of you beautiful \ud83e\udd70\ud83e\udd70\ud83e\udd70",
      "created_utc": 1666597343.0,
      "score": 1,
      "context": []
    },
    {
      "id": "itkl4wx",
      "author": "rileyyj001",
      "body": "Major kudos to you, OP!!! \n\nI specifically went out of my way to get a Happy Meal the other day because I desperately wanted one of the trick-or-treat Halloween buckets! It was so much fun to feel like a kid again, and to kind of let go of the ED a little. \ud83d\udc7b  \ud83c\udf5f",
      "created_utc": 1666606423.0,
      "score": 1,
      "context": []
    }
  ]
}