{
  "id": "daqlji",
  "subreddit": "AnorexiaNervosa",
  "author": "fundamentallylikable",
  "created_utc": 1569731228.0,
  "title": "I cope through memes",
  "selftext": "",
  "url": "https://i.redd.it/486zzoqcngp31.jpg",
  "score": 388,
  "num_comments": 11,
  "comments": [
    {
      "id": "f1stb4e",
      "author": "KaidenKami",
      "body": "Me 2! I mainly cope with my ed in memes! :D",
      "created_utc": 1569733773.0,
      "score": 10,
      "context": []
    },
    {
      "id": "f22zf59",
      "author": "irlbrat",
      "body": "Anyone else like genuinely prefer Diet Coke tho? I just hate the way regular soda tastes.",
      "created_utc": 1569901053.0,
      "score": 6,
      "context": []
    },
    {
      "id": "f1sz2bc",
      "author": "None",
      "body": "Yep delicious breakfast lunch dinner",
      "created_utc": 1569736231.0,
      "score": 4,
      "context": []
    },
    {
      "id": "f1vnz61",
      "author": "erinalexasotelo",
      "body": "I came across this post while eating a bowl of lettuce with mustard on it. It\u2019s totally a meal lol",
      "created_utc": 1569773555.0,
      "score": 2,
      "context": []
    },
    {
      "id": "f1xtj2d",
      "author": "Lisss19",
      "body": "This is pretty much me \ud83e\udd37\ud83c\udffc\u200d\u2640\ufe0f",
      "created_utc": 1569803809.0,
      "score": 2,
      "context": []
    },
    {
      "id": "f53p28n",
      "author": "annoymous2049",
      "body": "yo if u drink diet coke for breakfast like mood",
      "created_utc": 1571962301.0,
      "score": 1,
      "context": []
    },
    {
      "id": "f54juzz",
      "author": "OrphanDevour",
      "body": "Half cans of strawberry milk. \n\nDefense: it has the froots.",
      "created_utc": 1571984860.0,
      "score": 1,
      "context": []
    },
    {
      "id": "f62t5ds",
      "author": "None",
      "body": "Fact I learned recently: in an effort to refuce sugar consumption in the UK, Coca-Cola has a different recipe for their UK product. It has a lot less calories/sugar than the US/Canada version and is sweetened partially with Stevia. Here in Canada you can actually get calorie free Coca Cola sweetened entirely with Stevia!",
      "created_utc": 1572666738.0,
      "score": 1,
      "context": []
    },
    {
      "id": "f1vllw2",
      "author": "deepsigh8",
      "body": "Yes.",
      "created_utc": 1569772599.0,
      "score": 1,
      "context": []
    },
    {
      "id": "f5orsp3",
      "author": "None",
      "body": "Have you tried Coke Zero? I like that better than diet. Tastes less like the chemicals they add to make it \u00ab\u00a0diet\u00a0\u00bb.",
      "created_utc": 1572328849.0,
      "score": 2,
      "context": [
        {
          "id": "f22zf59",
          "author": "irlbrat",
          "body": "Anyone else like genuinely prefer Diet Coke tho? I just hate the way regular soda tastes.",
          "created_utc": 1569901053.0
        }
      ]
    },
    {
      "id": "f61q8wb",
      "author": "irlbrat",
      "body": "I haven\u2019t but I\u2019ll try it one day!",
      "created_utc": 1572644318.0,
      "score": 1,
      "context": [
        {
          "id": "f22zf59",
          "author": "irlbrat",
          "body": "Anyone else like genuinely prefer Diet Coke tho? I just hate the way regular soda tastes.",
          "created_utc": 1569901053.0
        },
        {
          "id": "f5orsp3",
          "author": "None",
          "body": "Have you tried Coke Zero? I like that better than diet. Tastes less like the chemicals they add to make it \u00ab\u00a0diet\u00a0\u00bb.",
          "created_utc": 1572328849.0
        }
      ]
    }
  ]
}