{
  "id": "ih1pcu",
  "subreddit": "AnorexiaNervosa",
  "author": "careful_hot",
  "created_utc": 1598458160.0,
  "title": "I ate a whole ass pizza and drunk vanilla iced cappuccino with it!!",
  "selftext": "That's it. Sounds like a normal thing, but even like a week ago it would seem as sth impossible for me to do. I'm so happy!",
  "url": "https://www.reddit.com/r/AnorexiaNervosa/comments/ih1pcu/i_ate_a_whole_ass_pizza_and_drunk_vanilla_iced/",
  "score": 237,
  "num_comments": 17,
  "comments": [
    {
      "id": "g2xfon9",
      "author": "LischenVonEngels",
      "body": "Three cheers for OP! Three cheers for OP!",
      "created_utc": 1598461722.0,
      "score": 22,
      "context": []
    },
    {
      "id": "g2xijyv",
      "author": "lillynight",
      "body": "Yummy!!! Now focus on the enjoyment that you had while doing that and don\u2019t forget it! You got this!",
      "created_utc": 1598463048.0,
      "score": 11,
      "context": []
    },
    {
      "id": "g2xdya5",
      "author": "LennyGal",
      "body": "congrats!! im proud of you :)",
      "created_utc": 1598460914.0,
      "score": 9,
      "context": []
    },
    {
      "id": "g2y9uqc",
      "author": "WideAtmosphere",
      "body": "Yay! Fuel the machine!   \nThat really is awesome! Pizza is one of the joys of LIFE!",
      "created_utc": 1598475436.0,
      "score": 5,
      "context": []
    },
    {
      "id": "g2xk6ue",
      "author": "what-are-f33ling5",
      "body": "So proud of you!",
      "created_utc": 1598463810.0,
      "score": 5,
      "context": []
    },
    {
      "id": "g2xw96m",
      "author": "phantasmaldream",
      "body": "proud of you!! :-)",
      "created_utc": 1598469235.0,
      "score": 3,
      "context": []
    },
    {
      "id": "g2xzl6a",
      "author": "icantsleepxoxo",
      "body": "Yay go you! Pizza is my absolute fear food so I\u2019m so proud of you!",
      "created_utc": 1598470775.0,
      "score": 3,
      "context": []
    },
    {
      "id": "g2yajde",
      "author": "None",
      "body": "[deleted]",
      "created_utc": 1598475755.0,
      "score": 3,
      "context": []
    },
    {
      "id": "g2yeihd",
      "author": "STAR-Gritz",
      "body": "HELL YEAH!! YOU GO GIRL!",
      "created_utc": 1598477632.0,
      "score": 3,
      "context": []
    },
    {
      "id": "g2ysplj",
      "author": "sufficiently_sp00ked",
      "body": "YOU'RE AMAZING AND YOU DESERVE DELICIOUS PIZZA! Proud of you!!!",
      "created_utc": 1598484829.0,
      "score": 3,
      "context": []
    },
    {
      "id": "g304s9p",
      "author": "Emptyfulfillment",
      "body": "Sameee yooo hooorrayyyy giving our body what it needs!",
      "created_utc": 1598517074.0,
      "score": 2,
      "context": []
    },
    {
      "id": "g30murn",
      "author": "charouhas",
      "body": "I am so proud of you!!",
      "created_utc": 1598532884.0,
      "score": 2,
      "context": []
    },
    {
      "id": "g3c5899",
      "author": "None",
      "body": "[removed]",
      "created_utc": 1598779503.0,
      "score": 2,
      "context": []
    },
    {
      "id": "g2xwjq5",
      "author": "CarlWheezerisbae96",
      "body": "HIP HIP HOORAY",
      "created_utc": 1598469371.0,
      "score": 10,
      "context": [
        {
          "id": "g2xfon9",
          "author": "LischenVonEngels",
          "body": "Three cheers for OP! Three cheers for OP!",
          "created_utc": 1598461722.0
        }
      ]
    },
    {
      "id": "g2y9ff5",
      "author": "careful_hot",
      "body": "It used to be my gwar food too, that's why i'm soooo happy i was able to enjoy it!",
      "created_utc": 1598475243.0,
      "score": 5,
      "context": [
        {
          "id": "g2xzl6a",
          "author": "icantsleepxoxo",
          "body": "Yay go you! Pizza is my absolute fear food so I\u2019m so proud of you!",
          "created_utc": 1598470775.0
        }
      ]
    },
    {
      "id": "g2yap6z",
      "author": "careful_hot",
      "body": "It was! Thanks!",
      "created_utc": 1598475831.0,
      "score": 3,
      "context": [
        {
          "id": "g2yajde",
          "author": "None",
          "body": "[deleted]",
          "created_utc": 1598475755.0
        }
      ]
    },
    {
      "id": "g3cbecb",
      "author": "careful_hot",
      "body": "It was zoo toasty! Thanks!",
      "created_utc": 1598785835.0,
      "score": 1,
      "context": [
        {
          "id": "g3c5899",
          "author": "None",
          "body": "[removed]",
          "created_utc": 1598779503.0
        }
      ]
    },
    {
      "id": "g2ycxss",
      "author": "None",
      "body": "[deleted]",
      "created_utc": 1598476891.0,
      "score": 3,
      "context": [
        {
          "id": "g2yajde",
          "author": "None",
          "body": "[deleted]",
          "created_utc": 1598475755.0
        },
        {
          "id": "g2yap6z",
          "author": "careful_hot",
          "body": "It was! Thanks!",
          "created_utc": 1598475831.0
        }
      ]
    },
    {
      "id": "g2yf8ej",
      "author": "careful_hot",
      "body": "Do it!! I'm so happy for you!",
      "created_utc": 1598477977.0,
      "score": 1,
      "context": [
        {
          "id": "g2yajde",
          "author": "None",
          "body": "[deleted]",
          "created_utc": 1598475755.0
        },
        {
          "id": "g2yap6z",
          "author": "careful_hot",
          "body": "It was! Thanks!",
          "created_utc": 1598475831.0
        },
        {
          "id": "g2ycxss",
          "author": "None",
          "body": "[deleted]",
          "created_utc": 1598476891.0
        }
      ]
    }
  ]
}