{
  "id": "18yoxco",
  "subreddit": "ARFID",
  "author": "hopefullythiswillend",
  "created_utc": 1704404812.0,
  "title": "DAE have physical hunger symptoms but not actually want to eat?",
  "selftext": "I don\u2019t know how to explain it but my stomach is hungry but my brain isn\u2019t in the mood to eat sometimes so I just don\u2019t eat anything. Has anyone else experienced this?",
  "url": "https://www.reddit.com/r/ARFID/comments/18yoxco/dae_have_physical_hunger_symptoms_but_not/",
  "score": 84,
  "num_comments": 27,
  "comments": [
    {
      "id": "kgckn36",
      "author": "LowRhubarb5668",
      "body": "Yep, I hate it as I also have ADHD so I will push off eating or just forget that I need to eat something. I will do so until I feel like I\u2019m going to pass out which makes it worse as I have to eat something that is solid but everything isn\u2019t appealing or acceptable. I will usually just making one of the quick meals/snacks I had been preferring recently and just eat that the best I can.",
      "created_utc": 1704408819.0,
      "score": 27,
      "context": []
    },
    {
      "id": "kgcbw54",
      "author": "Ok-Heart9769",
      "body": "All the timeeeee",
      "created_utc": 1704405810.0,
      "score": 18,
      "context": []
    },
    {
      "id": "kgcd9os",
      "author": "underinfinitebluesky",
      "body": "Yuppppppp",
      "created_utc": 1704406280.0,
      "score": 11,
      "context": []
    },
    {
      "id": "kgcdqiy",
      "author": "Beauty_Hunter22",
      "body": "basically my constant state, yeah \ud83d\ude2c",
      "created_utc": 1704406444.0,
      "score": 10,
      "context": []
    },
    {
      "id": "kgf1139",
      "author": "LemonfishSoda",
      "body": "Yup. And unfortunately, the hungrier I get, the narrower the list of options my brain will deem edible.",
      "created_utc": 1704452577.0,
      "score": 10,
      "context": []
    },
    {
      "id": "kgcgdob",
      "author": "two-of-me",
      "body": "Yep that\u2019s why I drink Boost. Just chug and get it over with.",
      "created_utc": 1704407366.0,
      "score": 7,
      "context": []
    },
    {
      "id": "kgctwoy",
      "author": "None",
      "body": "Always. I\u2019ll feel weak, hangryyyyy, stomach growling and I\u2019ll literally do every chore in the house before I\u2019d make the effort to open a bag of chips",
      "created_utc": 1704412239.0,
      "score": 5,
      "context": []
    },
    {
      "id": "kgcwx6i",
      "author": "Both_Fox_1774",
      "body": "My kiddo has this and we have tried lots of things but sometimes smelling foods helps him start getting an appetite and popsicles and icecream tends to get him started but sometimes nothing works!  When I had this bc of terrible anxiety I would make ACV water and drinks that to start my appetite up but have not tried it with my kid since they have debilitating stomach issues and ACV would probably make it way worse.  I\u2019m so sorry you are dealing with this it\u2019s so not easy.",
      "created_utc": 1704413371.0,
      "score": 4,
      "context": []
    },
    {
      "id": "kgdb2am",
      "author": "DMaC1105",
      "body": "I live in a perpetual state of being hungry but not wanting to eat anything. Some of it comes from meds lowering my appetite but even before the meds I went through periods where I was tired of all my safe foods. It got boring. I\u2019m actually in one of those phases now.",
      "created_utc": 1704418689.0,
      "score": 3,
      "context": []
    },
    {
      "id": "kgcnvx6",
      "author": "transaltalt",
      "body": "yeah often i feel hungry in my stomach but still have the full sensation in my throat",
      "created_utc": 1704409998.0,
      "score": 3,
      "context": []
    },
    {
      "id": "kgcueph",
      "author": "mercurys-daughter",
      "body": "Yup the disorder voice in my head is just like nah don\u2019t eat anyway",
      "created_utc": 1704412426.0,
      "score": 3,
      "context": []
    },
    {
      "id": "kge06lb",
      "author": "RecommendationTop362",
      "body": "I just went through this for a whole week. I ended up having to get some iv fluids on Monday and I'm back to eating some plain chicken with a tiny bit of BBQ sauce for flavour as im working my stomach back up to eating other foods.. but my body basically started breaking down, I felt super fatigued and had 0 energy, took a few days off from work and haven't been back yet. I am sick with a cold which usually stunts my appetite but idk this time around... I chose to just not eat anything at all. Worst 2 weeks of my life",
      "created_utc": 1704429074.0,
      "score": 3,
      "context": []
    },
    {
      "id": "kgclv25",
      "author": "little-red-cap",
      "body": "Yes. Constantly. It\u2019s terrible. \ud83d\ude43\ud83e\udee0\ud83e\udee0",
      "created_utc": 1704409256.0,
      "score": 2,
      "context": []
    },
    {
      "id": "kgczap9",
      "author": "sketchnscribble",
      "body": "I deal with this all the time.",
      "created_utc": 1704414259.0,
      "score": 2,
      "context": []
    },
    {
      "id": "kgd4foo",
      "author": "HuskyPancake",
      "body": "Yeah. Not having any interest in food or desire to force myself to eat usually takes over.",
      "created_utc": 1704416182.0,
      "score": 2,
      "context": []
    },
    {
      "id": "kgdgdso",
      "author": "Mx-Helix-pomatia",
      "body": "This is so real \ud83d\ude14",
      "created_utc": 1704420750.0,
      "score": 2,
      "context": []
    },
    {
      "id": "kge5ljo",
      "author": "pnkknife",
      "body": "I feel like it\u2019s because none of my safe foods have fiber or provide much nutritional value",
      "created_utc": 1704431709.0,
      "score": 2,
      "context": []
    },
    {
      "id": "kggkjg3",
      "author": "Nthorpe1996",
      "body": "I get this ALL THE F\u2019ING TIME!! It\u2019s to the point that if I try and make myself eat, I feel sick after. My dr says it\u2019s a result of how sick I\u2019ve been with my stomach problems for the last 2 years.",
      "created_utc": 1704476169.0,
      "score": 2,
      "context": []
    },
    {
      "id": "kgcjv18",
      "author": "scared_sage",
      "body": "Yep",
      "created_utc": 1704408547.0,
      "score": 1,
      "context": []
    },
    {
      "id": "kgetbyf",
      "author": "OpheliaJade2382",
      "body": "Yup. I can sometimes manage white rice or smoothies when I feel like this (which I currently am). Basically anything that doesn\u2019t taste strongly. Anything else makes me nauseous",
      "created_utc": 1704447010.0,
      "score": 1,
      "context": []
    },
    {
      "id": "kggj66a",
      "author": "orangejuicery",
      "body": "Everyday..",
      "created_utc": 1704475709.0,
      "score": 1,
      "context": []
    },
    {
      "id": "kgjy40v",
      "author": "earlnacht",
      "body": "Yeah. Smoothies help.",
      "created_utc": 1704523626.0,
      "score": 1,
      "context": []
    },
    {
      "id": "kgy5xzd",
      "author": "Direct_Language_24",
      "body": "I struggle with that alot yea",
      "created_utc": 1704746596.0,
      "score": 1,
      "context": []
    },
    {
      "id": "kgcp0u0",
      "author": "whatdoidonowdamnit",
      "body": "I\u2019ll get hungry at the worst times, like in the shower or on the bus. Then by the time I\u2019m able to eat I forgot I was hungry. I keep peanuts in the kitchen because it\u2019s a snack food my kids won\u2019t inhale.",
      "created_utc": 1704410414.0,
      "score": 4,
      "context": [
        {
          "id": "kgckn36",
          "author": "LowRhubarb5668",
          "body": "Yep, I hate it as I also have ADHD so I will push off eating or just forget that I need to eat something. I will do so until I feel like I\u2019m going to pass out which makes it worse as I have to eat something that is solid but everything isn\u2019t appealing or acceptable. I will usually just making one of the quick meals/snacks I had been preferring recently and just eat that the best I can.",
          "created_utc": 1704408819.0
        }
      ]
    },
    {
      "id": "kgcnykm",
      "author": "transaltalt",
      "body": "stomach ache time",
      "created_utc": 1704410025.0,
      "score": 6,
      "context": [
        {
          "id": "kgcgdob",
          "author": "two-of-me",
          "body": "Yep that\u2019s why I drink Boost. Just chug and get it over with.",
          "created_utc": 1704407366.0
        }
      ]
    },
    {
      "id": "kge3rp8",
      "author": "Jade-Balfour",
      "body": "If this kid is willing and wants to try, maybe use the *diluted* ACV as more like a mouthwash and spit it out after sipping it. Alternatively try something similar but with bitters. (Bitter stuff signals to your body to produce bile and start the digestive process). This definitely won't work for everyone (and probably only a small subset of people here) but when I've had my health under control otherwise, something sour or bitter would help me get my appetite going (I usually picked bitters in plain soda water or ice water). Currently past the point that it can help me, but since it helped before just putting it out there.\n\n[more info](https://health.clevelandclinic.org/digestive-bitters)",
      "created_utc": 1704430796.0,
      "score": 3,
      "context": [
        {
          "id": "kgcwx6i",
          "author": "Both_Fox_1774",
          "body": "My kiddo has this and we have tried lots of things but sometimes smelling foods helps him start getting an appetite and popsicles and icecream tends to get him started but sometimes nothing works!  When I had this bc of terrible anxiety I would make ACV water and drinks that to start my appetite up but have not tried it with my kid since they have debilitating stomach issues and ACV would probably make it way worse.  I\u2019m so sorry you are dealing with this it\u2019s so not easy.",
          "created_utc": 1704413371.0
        }
      ]
    },
    {
      "id": "kge0jj5",
      "author": "RecommendationTop362",
      "body": "I also have adhd though so it's a common occurrence daily that I forget to eat and I end up having 1 meal around 11pm... sometimes I can feel myself basically starving but I can't bring myself to do anything about it...",
      "created_utc": 1704429245.0,
      "score": 3,
      "context": [
        {
          "id": "kge06lb",
          "author": "RecommendationTop362",
          "body": "I just went through this for a whole week. I ended up having to get some iv fluids on Monday and I'm back to eating some plain chicken with a tiny bit of BBQ sauce for flavour as im working my stomach back up to eating other foods.. but my body basically started breaking down, I felt super fatigued and had 0 energy, took a few days off from work and haven't been back yet. I am sick with a cold which usually stunts my appetite but idk this time around... I chose to just not eat anything at all. Worst 2 weeks of my life",
          "created_utc": 1704429074.0
        }
      ]
    }
  ]
}